{
  "members":[
    {
      "name":"x",
      "type":"float"
    },
    {
      "name":"y",
      "type":"float"
    },
    {
      "name":"z",
      "type":"float"
    }
  ],
  "constants":[
    {
      "name":"AXIS_X",
      "value":"0"
    },
    {
      "name":"AXIS_Y",
      "value":"1"
    },
    {
      "name":"AXIS_Z",
      "value":"2"
    },
    {
      "name":"ZERO",
      "value":"Vector3( 0, 0, 0 )"
    },
    {
      "name":"ONE",
      "value":"Vector3( 1, 1, 1 )"
    },
    {
      "name":"INF",
      "value":"Vector3( inf, inf, inf )"
    },
    {
      "name":"LEFT",
      "value":"Vector3( -1, 0, 0 )"
    },
    {
      "name":"RIGHT",
      "value":"Vector3( 1, 0, 0 )"
    },
    {
      "name":"UP",
      "value":"Vector3( 0, 1, 0 )"
    },
    {
      "name":"DOWN",
      "value":"Vector3( 0, -1, 0 )"
    },
    {
      "name":"FORWARD",
      "value":"Vector3( 0, 0, -1 )"
    },
    {
      "name":"BACK",
      "value":"Vector3( 0, 0, 1 )"
    }
  ],
  "methods":[
    {
      "returns":"Vector3",
      "name":"abs"
    },
    {
      "returns":"float",
      "name":"angle_to",
      "args":[
        {
          "name":"to",
          "type":"Vector3"
        }
      ]
    },
    {
      "returns":"Vector3",
      "name":"bounce",
      "args":[
        {
          "name":"n",
          "type":"Vector3"
        }
      ]
    },
    {
      "returns":"Vector3",
      "name":"ceil"
    },
    {
      "returns":"Vector3",
      "name":"cross",
      "args":[
        {
          "name":"b",
          "type":"Vector3"
        }
      ]
    },
    {
      "returns":"Vector3",
      "name":"cubic_interpolate",
      "args":[
        {
          "name":"b",
          "type":"Vector3"
        },
        {
          "name":"pre_a",
          "type":"Vector3"
        },
        {
          "name":"post_b",
          "type":"Vector3"
        },
        {
          "name":"t",
          "type":"float"
        }
      ]
    },
    {
      "returns":"Vector3",
      "name":"direction_to",
      "args":[
        {
          "name":"b",
          "type":"Vector3"
        }
      ]
    },
    {
      "returns":"float",
      "name":"distance_squared_to",
      "args":[
        {
          "name":"b",
          "type":"Vector3"
        }
      ]
    },
    {
      "returns":"float",
      "name":"distance_to",
      "args":[
        {
          "name":"b",
          "type":"Vector3"
        }
      ]
    },
    {
      "returns":"float",
      "name":"dot",
      "args":[
        {
          "name":"b",
          "type":"Vector3"
        }
      ]
    },
    {
      "returns":"Vector3",
      "name":"floor"
    },
    {
      "returns":"Vector3",
      "name":"inverse"
    },
    {
      "returns":"bool",
      "name":"is_normalized"
    },
    {
      "returns":"float",
      "name":"length"
    },
    {
      "returns":"float",
      "name":"length_squared"
    },
    {
      "returns":"Vector3",
      "name":"linear_interpolate",
      "args":[
        {
          "name":"b",
          "type":"Vector3"
        },
        {
          "name":"t",
          "type":"float"
        }
      ]
    },
    {
      "returns":"int",
      "name":"max_axis"
    },
    {
      "returns":"int",
      "name":"min_axis"
    },
    {
      "returns":"Vector3",
      "name":"normalized"
    },
    {
      "returns":"Basis",
      "name":"outer",
      "args":[
        {
          "name":"b",
          "type":"Vector3"
        }
      ]
    },
    {
      "returns":"Vector3",
      "name":"project",
      "args":[
        {
          "name":"b",
          "type":"Vector3"
        }
      ]
    },
    {
      "returns":"Vector3",
      "name":"reflect",
      "args":[
        {
          "name":"n",
          "type":"Vector3"
        }
      ]
    },
    {
      "returns":"Vector3",
      "name":"rotated",
      "args":[
        {
          "name":"axis",
          "type":"Vector3"
        },
        {
          "name":"phi",
          "type":"float"
        }
      ]
    },
    {
      "returns":"Vector3",
      "name":"round"
    },
    {
      "returns":"Vector3",
      "name":"slerp",
      "args":[
        {
          "name":"b",
          "type":"Vector3"
        },
        {
          "name":"t",
          "type":"float"
        }
      ]
    },
    {
      "returns":"Vector3",
      "name":"slide",
      "args":[
        {
          "name":"n",
          "type":"Vector3"
        }
      ]
    },
    {
      "returns":"Vector3",
      "name":"snapped",
      "args":[
        {
          "name":"by",
          "type":"Vector3"
        }
      ]
    },
    {
      "returns":"Basis",
      "name":"to_diagonal_matrix"
    }
  ],
  "name":"Vector3",
  "inherits":null,
  "built_in":true
}